dmodel/__init__.py
dmodel/context.py
dmodel/descriptors.py
dmodel/enums.py
dmodel/form.py
dmodel/functions/__init__.py
dmodel/functions/iteration.py
dmodel/model.py
dmodel/models/__init__.py
dmodel/models/facility.py
dmodel/models/person.py
dmodel/models/profile.py
dmodel/models/user.py
dmodel/models/visit.py
dmodel/regex.py
dmodel-0.0.6.dist-info/WHEEL
dmodel-0.0.6.dist-info/METADATA
dmodel-0.0.6.dist-info/RECORD
